djcelery_ses/__init__.py
djcelery_ses/admin.py
djcelery_ses/backends.py
djcelery_ses/models.py
djcelery_ses/tasks.py
djcelery_ses/test_runner.py
djcelery_ses/tests.py
djcelery_ses/urls.py
djcelery_ses/utils.py
djcelery_ses/views.py
djcelery_ses/migrations/0001_initial.py
djcelery_ses/migrations/__init__.py
djcelery_ses/south_migrations/0001_initial.py
djcelery_ses/south_migrations/0002_auto__del_field_messagelog_body__add_field_messagelog_subject.py
djcelery_ses/south_migrations/__init__.py
django_celery_ses-3.1.1.dist-info/LICENSE.txt
django_celery_ses-3.1.1.dist-info/METADATA
django_celery_ses-3.1.1.dist-info/WHEEL
django_celery_ses-3.1.1.dist-info/top_level.txt
django_celery_ses-3.1.1.dist-info/RECORD
